synct/__init__.py
synct/__main__.py
synct/bzilla.py
synct/config.py
synct/git.py
synct/gsheet.py
synct/jira.py
synct/logger.py
synct/source.py
synct/synct.py
synct/tsheet.py
synct/xsheet.py
synct/ysheet.py
tests/__init__.py
tests/test_synct.py
tests/test_synct_jira.py
synct-1.8.2.dist-info/AUTHORS
synct-1.8.2.dist-info/COPYING
synct-1.8.2.dist-info/METADATA
synct-1.8.2.dist-info/WHEEL
synct-1.8.2.dist-info/entry_points.txt
synct-1.8.2.dist-info/top_level.txt
synct-1.8.2.dist-info/RECORD
