Metadata-Version: 2.1
Name: synct
Version: 1.8.2
Summary: Transform data from source to Google or Excel spreadsheet
Home-page: https://github.com/ari3s/synct
Author: Jan Beran
Author-email: ari3s.git@gmail.com
License: GPL-3.0-or-later
License-File: COPYING
License-File: AUTHORS
Requires-Dist: jira
Requires-Dist: google-api-python-client
Requires-Dist: google-auth-oauthlib
Requires-Dist: openpyxl
Requires-Dist: pandas
Requires-Dist: pyperclip
Requires-Dist: pyyaml
Requires-Dist: python-bugzilla
